AUTHORS.rst
CONTRIBUTING.rst
HISTORY.rst
LICENSE.txt
MANIFEST.in
README.rst
setup.cfg
setup.py
versioneer.py
docs/Makefile
docs/api.rst
docs/authors.rst
docs/conf.py
docs/contributing.rst
docs/history.rst
docs/index.rst
docs/installation.rst
docs/make.bat
docs/readme.rst
docs/usage.rst
tests/__init__.py
tests/test_core.py
xnumpy/__init__.py
xnumpy/_version.py
xnumpy/core.py
xnumpy.egg-info/PKG-INFO
xnumpy.egg-info/SOURCES.txt
xnumpy.egg-info/dependency_links.txt
xnumpy.egg-info/not-zip-safe
xnumpy.egg-info/requires.txt
xnumpy.egg-info/top_level.txt