Metadata-Version: 1.1
Name: xnumpy
Version: 0.1.0
Summary: A Python utility library for working with expanded NumPy arrays.
Home-page: https://github.com/jakirkham/xnumpy
Author: John Kirkham
Author-email: kirkhamj@janelia.hhmi.org
License: BSD 3-Clause
Keywords: xnumpy
Platform: UNKNOWN
Classifier: Development Status :: 2 - Pre-Alpha
Classifier: Intended Audience :: Developers
Classifier: License :: OSI Approved :: BSD License
Classifier: Natural Language :: English
Classifier: Programming Language :: Python :: 2
Classifier: Programming Language :: Python :: 2.7
Classifier: Programming Language :: Python :: 3
Classifier: Programming Language :: Python :: 3.4
Classifier: Programming Language :: Python :: 3.5
